{"meta":{"code":200,"requestId":"5d293189e97dfb002c8b0e96"},"response":{"venue":{"id":"4b649f72f964a52019c32ae3","name":"Cracker Barrel Old Country Store","contact":{"phone":"8136620607","formattedPhone":"(813) 662-0607","twitter":"crackerbarrel"},"location":{"address":"1880 E State Road 60","lat":27.938506961180366,"lng":-82.25678675619477,"labeledLatLngs":[{"label":"display","lat":27.938506961180366,"lng":-82.25678675619477}],"postalCode":"33594","cc":"US","city":"Valrico","state":"FL","country":"United States","formattedAddress":["1880 E State Road 60","Valrico, FL 33594","United States"]},"canonicalUrl":"https:\/\/foursquare.com\/v\/cracker-barrel-old-country-store\/4b649f72f964a52019c32ae3","categories":[{"id":"4bf58dd8d48988d14e941735","name":"American Restaurant","pluralName":"American Restaurants","shortName":"American","icon":{"prefix":"https:\/\/ss3.4sqi.net\/img\/categories_v2\/food\/default_","suffix":".png"},"primary":true}],"verified":true,"stats":{"tipCount":37},"url":"https:\/\/locations.crackerbarrel.com\/fl\/valrico\/534\/","price":{"tier":2,"message":"Moderate","currency":"$"},"hasMenu":true,"likes":{"count":117,"groups":[{"type":"others","count":117,"items":[]}],"summary":"117 Likes"},"dislike":false,"ok":false,"rating":8.5,"ratingColor":"73CF42","ratingSignals":160,"menu":{"type":"Menu","label":"Menu","anchor":"View Menu","url":"https:\/\/foursquare.com\/v\/cracker-barrel-old-country-store\/4b649f72f964a52019c32ae3\/menu","mobileUrl":"https:\/\/foursquare.com\/v\/4b649f72f964a52019c32ae3\/device_menu"},"allowMenuUrlEdit":true,"beenHere":{"count":0,"unconfirmedCount":0,"marked":false,"lastCheckinExpiredAt":0},"specials":{"count":0,"items":[]},"photos":{"count":93,"groups":[{"type":"checkin","name":"Friends' check-in photos","count":0,"items":[]},{"type":"venue","name":"Venue photos","count":93,"items":[{"id":"4fe52ad0e4b00cda58a3ad64","createdAt":1340418768,"source":{"name":"Foursquare for iOS","url":"https:\/\/foursquare.com\/download\/#\/iphone"},"prefix":"https:\/\/fastly.4sqi.net\/img\/general\/","suffix":"\/WiYaR3l6l8aEBkeEPmw34p-9NLEdXPDuvH21ESXjDpc.jpg","width":720,"height":540,"user":{"id":"931274","firstName":"Tatiana","lastName":"Whited","gender":"female","photo":{"prefix":"https:\/\/fastly.4sqi.net\/img\/user\/","suffix":"\/YTONOERIKG4QWZJL.jpg"}},"visibility":"public"},{"id":"4fd36aefe4b03f13ec802261","createdAt":1339255535,"source":{"name":"Foursquare for iOS","url":"https:\/\/foursquare.com\/download\/#\/iphone"},"prefix":"https:\/\/fastly.4sqi.net\/img\/general\/","suffix":"\/CJY79WjJEvaeAXrXbsugKpZ_I_khfrQBwPzY7hs5YK0.jpg","width":537,"height":720,"user":{"id":"16168927","firstName":"Megan","lastName":"Maze","gender":"female","photo":{"prefix":"https:\/\/fastly.4sqi.net\/img\/user\/","suffix":"\/16168927-M5XWUMLH24DVXRY2.jpg"}},"visibility":"public"}]}],"summary":"0 photos"},"reasons":{"count":1,"items":[{"summary":"Lots of people like this place","type":"general","reasonName":"rawLikesReason"}]},"description":"Visit Cracker Barrel Restaurant and Old Country Store, where pleasing people with our delicious homestyle cooking & gracious service defines our country spirit.","storeId":"534","page":{"pageInfo":{"description":"Visit Cracker Barrel Restaurant and Old Country Store, where pleasing people with our delicious homestyle cooking & gracious service defines our country spirit.","links":{"count":1,"items":[{"url":"https:\/\/locations.crackerbarrel.com\/ca\/rialto\/765\/"}]}},"user":{"id":"59646403","firstName":"Cracker Barrel","gender":"none","photo":{"prefix":"https:\/\/fastly.4sqi.net\/img\/user\/","suffix":"\/Q0MNRZ15WMWMDADE.jpg"},"type":"chain","tips":{"count":0},"lists":{"groups":[{"type":"created","count":2,"items":[]}]},"homeCity":"New York","bio":"","contact":{}}},"hereNow":{"count":0,"summary":"Nobody here","groups":[]},"createdAt":1264885618,"tips":{"count":37,"groups":[{"type":"others","name":"All tips","count":37,"items":[{"id":"5133eb44e4b006d9dadc26b5","createdAt":1362357060,"text":"Low Carb Food :-) lemon chicken with brown rice with veggies. Not bad for a nice low carb meal :-)","type":"user","canonicalUrl":"https:\/\/foursquare.com\/item\/5133eb44e4b006d9dadc26b5","lang":"en","likes":{"count":7,"groups":[{"type":"others","count":7,"items":[{"id":"100522884","firstName":"Jose","lastName":"Medrano","gender":"male","photo":{"prefix":"https:\/\/fastly.4sqi.net\/img\/user\/","suffix":"\/100522884-KDTTMWDRS4MFUTHT.jpg"}},{"id":"188014","firstName":"Mr.","lastName":"K. B.","gender":"male","photo":{"prefix":"https:\/\/fastly.4sqi.net\/img\/user\/","suffix":"\/188014_ez9kQvEj_JfWK1kxxUrZykHgGbNSuMyuKMLqJQ7eWANcaNVSlNeXmR4txJ0cck0pmWDARaf23.jpg"}}]}],"summary":"7 likes"},"logView":true,"agreeCount":8,"disagreeCount":0,"todo":{"count":1},"user":{"id":"48641223","firstName":"Yady","lastName":"Felix","gender":"female","photo":{"prefix":"https:\/\/fastly.4sqi.net\/img\/user\/","suffix":"\/ZPMWTHR5LDDIVAD5.jpg"}},"authorInteractionType":"liked"},{"id":"4d98c28b61a3a1cdbc7fd542","createdAt":1301856907,"text":"Cracker barrel never disappoints!","type":"user","canonicalUrl":"https:\/\/foursquare.com\/item\/4d98c28b61a3a1cdbc7fd542","lang":"en","likes":{"count":6,"groups":[{"type":"others","count":6,"items":[{"id":"5395445","firstName":"Britni","lastName":"Laboy","gender":"female","photo":{"prefix":"https:\/\/fastly.4sqi.net\/img\/user\/","suffix":"\/HT54JRA3C3FTTBOA.jpg"}},{"id":"48641223","firstName":"Yady","lastName":"Felix","gender":"female","photo":{"prefix":"https:\/\/fastly.4sqi.net\/img\/user\/","suffix":"\/ZPMWTHR5LDDIVAD5.jpg"}}]}],"summary":"6 likes"},"logView":true,"agreeCount":2,"disagreeCount":0,"todo":{"count":1},"user":{"id":"6776917","firstName":"Giselle","lastName":"D'Guerra","gender":"female","photo":{"prefix":"https:\/\/fastly.4sqi.net\/img\/user\/","suffix":"\/45QPX4TWWHUMQT4V.jpg"}}}]}]},"shortUrl":"http:\/\/4sq.com\/99D4TU","timeZone":"America\/New_York","listed":{"count":12,"groups":[{"type":"others","name":"Lists from other people","count":12,"items":[{"id":"4f63fcfbe4b0bf10117bba3a","name":"Home","description":"","type":"others","user":{"id":"6872541","firstName":"Johnny F","lastName":"Cannoy Sr","gender":"male","photo":{"prefix":"https:\/\/fastly.4sqi.net\/img\/user\/","suffix":"\/LBDKIMV5B2GRALXK.jpg"}},"editable":false,"public":true,"collaborative":false,"url":"\/user\/6872541\/list\/home","canonicalUrl":"https:\/\/foursquare.com\/user\/6872541\/list\/home","createdAt":1331952891,"updatedAt":1356944132,"followers":{"count":0},"listItems":{"count":19,"items":[{"id":"v4b649f72f964a52019c32ae3","createdAt":1332180235}]}},{"id":"4f53e0eae4b0ee60ba9049c1","name":"Best food in Brandon","description":"","type":"others","user":{"id":"1964346","firstName":"Brandon","lastName":"Wright","gender":"male","photo":{"prefix":"https:\/\/fastly.4sqi.net\/img\/user\/","suffix":"\/L3SMLGSUAQC1LKUO.jpg"}},"editable":false,"public":true,"collaborative":false,"url":"\/user\/1964346\/list\/best-food-in-brandon","canonicalUrl":"https:\/\/foursquare.com\/user\/1964346\/list\/best-food-in-brandon","createdAt":1330897130,"updatedAt":1330897423,"followers":{"count":1},"listItems":{"count":15,"items":[{"id":"v4b649f72f964a52019c32ae3","createdAt":1330897222}]}},{"id":"4fa6a893e4b017e938f8bbf1","name":"Restaurants","description":"","type":"others","user":{"id":"8594969","firstName":"David","lastName":"Greenhow","gender":"male","photo":{"prefix":"https:\/\/fastly.4sqi.net\/img\/user\/","suffix":"\/blank_boy.png","default":true}},"editable":false,"public":true,"collaborative":false,"url":"\/user\/8594969\/list\/restaurants","canonicalUrl":"https:\/\/foursquare.com\/user\/8594969\/list\/restaurants","createdAt":1336322195,"updatedAt":1361046034,"followers":{"count":0},"listItems":{"count":15,"items":[{"id":"v4b649f72f964a52019c32ae3","createdAt":1336852069}]}},{"id":"521ba18411d21804a05e8fea","name":"Best in Brandon","description":"","type":"others","user":{"id":"4434074","firstName":"Angela","lastName":"Hayer","gender":"female","photo":{"prefix":"https:\/\/fastly.4sqi.net\/img\/user\/","suffix":"\/5Y5JJU2TSARPTFFH.jpg"}},"editable":false,"public":true,"collaborative":false,"url":"\/angi27\/list\/best-in-brandon","canonicalUrl":"https:\/\/foursquare.com\/angi27\/list\/best-in-brandon","createdAt":1377542532,"updatedAt":1497540471,"followers":{"count":0},"listItems":{"count":22,"items":[{"id":"v4b649f72f964a52019c32ae3","createdAt":1377542677}]}}]}]},"hours":{"status":"Open until 11:00 PM","richStatus":{"entities":[],"text":"Open until 11:00 PM"},"isOpen":true,"isLocalHoliday":false,"dayData":[],"timeframes":[{"days":"Mon\u2013Thu, Sun","open":[{"renderedTime":"6:00 AM\u201310:00 PM"}],"segments":[]},{"days":"Fri\u2013Sat","includesToday":true,"open":[{"renderedTime":"6:00 AM\u201311:00 PM"}],"segments":[]}]},"popular":{"isOpen":false,"isLocalHoliday":false,"timeframes":[{"days":"Today","includesToday":true,"open":[{"renderedTime":"8:00 AM\u20132:00 PM"},{"renderedTime":"4:00 PM\u20139:00 PM"}],"segments":[]},{"days":"Sat","open":[{"renderedTime":"8:00 AM\u20133:00 PM"},{"renderedTime":"5:00 PM\u20138:00 PM"}],"segments":[]},{"days":"Sun","open":[{"renderedTime":"8:00 AM\u20138:00 PM"}],"segments":[]},{"days":"Mon","open":[{"renderedTime":"9:00 AM\u20131:00 PM"},{"renderedTime":"5:00 PM\u20137:00 PM"}],"segments":[]},{"days":"Tue","open":[{"renderedTime":"10:00 AM\u20131:00 PM"},{"renderedTime":"5:00 PM\u20138:00 PM"}],"segments":[]},{"days":"Wed","open":[{"renderedTime":"11:00 AM\u2013Noon"},{"renderedTime":"5:00 PM\u20138:00 PM"}],"segments":[]},{"days":"Thu","open":[{"renderedTime":"9:00 AM\u20131:00 PM"},{"renderedTime":"5:00 PM\u20138:00 PM"}],"segments":[]}]},"pageUpdates":{"count":1,"items":[]},"inbox":{"count":0,"items":[]},"attributes":{"groups":[{"type":"price","name":"Price","summary":"$$","count":1,"items":[{"displayName":"Price","displayValue":"$$","priceTier":2}]},{"type":"reservations","name":"Reservations","count":3,"items":[{"displayName":"Reservations","displayValue":"No"}]},{"type":"payments","name":"Credit Cards","summary":"Credit Cards","count":7,"items":[{"displayName":"Credit Cards","displayValue":"Yes (incl. Discover & Visa)"}]},{"type":"outdoorSeating","name":"Outdoor Seating","count":1,"items":[{"displayName":"Outdoor Seating","displayValue":"No"}]},{"type":"serves","name":"Menus","summary":"Dinner, Lunch & more","count":8,"items":[{"displayName":"Brunch","displayValue":"Brunch"},{"displayName":"Lunch","displayValue":"Lunch"},{"displayName":"Dinner","displayValue":"Dinner"}]},{"type":"drinks","name":"Drinks","summary":"Cocktails","count":5,"items":[{"displayName":"Cocktails","displayValue":"Cocktails"}]},{"type":"diningOptions","name":"Dining Options","count":5,"items":[{"displayName":"Delivery","displayValue":"No Delivery"}]}]},"bestPhoto":{"id":"4fe52ad0e4b00cda58a3ad64","createdAt":1340418768,"source":{"name":"Foursquare for iOS","url":"https:\/\/foursquare.com\/download\/#\/iphone"},"prefix":"https:\/\/fastly.4sqi.net\/img\/general\/","suffix":"\/WiYaR3l6l8aEBkeEPmw34p-9NLEdXPDuvH21ESXjDpc.jpg","width":720,"height":540,"visibility":"public"},"colors":{"highlightColor":{"photoId":"4fe52ad0e4b00cda58a3ad64","value":-2043728},"highlightTextColor":{"photoId":"4fe52ad0e4b00cda58a3ad64","value":-16777216},"algoVersion":3}}}}