{"meta":{"code":200,"requestId":"5d293959f129b500250348f5"},"response":{"venue":{"id":"4d629262b6b9a1cd16e29351","name":"Della's","contact":{"phone":"8136843354","formattedPhone":"(813) 684-3354"},"location":{"address":"608 Oakfield Dr","lat":27.93450835819368,"lng":-82.29204997113446,"labeledLatLngs":[{"label":"display","lat":27.93450835819368,"lng":-82.29204997113446}],"postalCode":"33511","cc":"US","city":"Brandon","state":"FL","country":"United States","formattedAddress":["608 Oakfield Dr","Brandon, FL 33511","United States"]},"canonicalUrl":"https:\/\/foursquare.com\/v\/dellas\/4d629262b6b9a1cd16e29351","categories":[{"id":"4bf58dd8d48988d14e941735","name":"American Restaurant","pluralName":"American Restaurants","shortName":"American","icon":{"prefix":"https:\/\/ss3.4sqi.net\/img\/categories_v2\/food\/default_","suffix":".png"},"primary":true}],"verified":false,"stats":{"tipCount":3},"price":{"tier":2,"message":"Moderate","currency":"$"},"hasMenu":true,"likes":{"count":9,"groups":[{"type":"others","count":9,"items":[{"id":"546477","firstName":"Roy","lastName":"Glasser","gender":"male","photo":{"prefix":"https:\/\/fastly.4sqi.net\/img\/user\/","suffix":"\/RGMZMEABVDZTWRMX.jpg"}},{"id":"7103338","firstName":"Jrgts","gender":"male","photo":{"prefix":"https:\/\/fastly.4sqi.net\/img\/user\/","suffix":"\/DI0A4AUOSSRSPYWW.jpg"}},{"id":"778722","firstName":"Ben","lastName":"Campbell","gender":"male","photo":{"prefix":"https:\/\/fastly.4sqi.net\/img\/user\/","suffix":"\/778722-1TLZFSFNGPD0YFT0.jpg"}},{"id":"22757168","firstName":"CJ","lastName":"Thomas","gender":"male","photo":{"prefix":"https:\/\/fastly.4sqi.net\/img\/user\/","suffix":"\/22757168-YIJXQZUKGBFUWOR1.jpg"}}]}],"summary":"9 Likes"},"dislike":false,"ok":false,"rating":7.4,"ratingColor":"C5DE35","ratingSignals":15,"menu":{"type":"Menu","label":"Menu","anchor":"View Menu","url":"https:\/\/foursquare.com\/v\/dellas\/4d629262b6b9a1cd16e29351\/menu","mobileUrl":"https:\/\/foursquare.com\/v\/4d629262b6b9a1cd16e29351\/device_menu"},"allowMenuUrlEdit":true,"beenHere":{"count":0,"unconfirmedCount":0,"marked":false,"lastCheckinExpiredAt":0},"specials":{"count":0,"items":[]},"photos":{"count":5,"groups":[{"type":"checkin","name":"Friends' check-in photos","count":0,"items":[]},{"type":"venue","name":"Venue photos","count":5,"items":[{"id":"5bd35826a35dce002c3aa527","createdAt":1540577318,"source":{"name":"Swarm for iOS","url":"https:\/\/www.swarmapp.com"},"prefix":"https:\/\/fastly.4sqi.net\/img\/general\/","suffix":"\/70098888_ed1BuoivufnCOTt4QqDPZZcCUyLR1_nyta_abfzJT4w.jpg","width":1440,"height":1920,"user":{"id":"70098888","firstName":"H","lastName":"H","gender":"female","photo":{"prefix":"https:\/\/fastly.4sqi.net\/img\/user\/","suffix":"\/70098888-0DY5VOJ0SG3US0SU.jpg"}},"visibility":"public"},{"id":"53b422fe498e15bc00bafc6e","createdAt":1404314366,"source":{"name":"Foursquare for Android","url":"https:\/\/foursquare.com\/download\/#\/android"},"prefix":"https:\/\/fastly.4sqi.net\/img\/general\/","suffix":"\/7943370_81cr6WanVmOXfHqDDrfGhNkdyfpzexoCGgaLczRss-8.jpg","width":960,"height":960,"user":{"id":"7943370","firstName":"Doug","lastName":"Gilmore","gender":"male","photo":{"prefix":"https:\/\/fastly.4sqi.net\/img\/user\/","suffix":"\/JUZKC52CYCL1EH5R.jpg"}},"visibility":"public"}]}],"summary":"0 photos"},"reasons":{"count":0,"items":[]},"hereNow":{"count":0,"summary":"Nobody here","groups":[]},"createdAt":1298305634,"tips":{"count":3,"groups":[{"type":"others","name":"All tips","count":3,"items":[{"id":"4f06471a77c84c826518cac4","createdAt":1325811482,"text":"Great food, gotta love the Jazz music!","type":"user","canonicalUrl":"https:\/\/foursquare.com\/item\/4f06471a77c84c826518cac4","lang":"en","likes":{"count":1,"groups":[{"type":"others","count":1,"items":[]}],"summary":"1 like"},"logView":true,"agreeCount":1,"disagreeCount":0,"todo":{"count":0},"user":{"id":"19085247","firstName":"Tim","gender":"male","photo":{"prefix":"https:\/\/fastly.4sqi.net\/img\/user\/","suffix":"\/S2JMPJ5MXI1FFHPI.jpg"}}},{"id":"58949a770b7e93429a58830b","createdAt":1486133879,"text":"Great selections of homemade soups and sandwiches. They serve beer and wine, too.","type":"user","canonicalUrl":"https:\/\/foursquare.com\/item\/58949a770b7e93429a58830b","lang":"en","likes":{"count":0,"groups":[]},"logView":true,"agreeCount":0,"disagreeCount":0,"todo":{"count":0},"user":{"id":"7103338","firstName":"Jrgts","gender":"male","photo":{"prefix":"https:\/\/fastly.4sqi.net\/img\/user\/","suffix":"\/DI0A4AUOSSRSPYWW.jpg"}},"authorInteractionType":"liked"}]}]},"shortUrl":"http:\/\/4sq.com\/dXv3sS","timeZone":"America\/New_York","listed":{"count":1,"groups":[{"type":"others","name":"Lists from other people","count":1,"items":[{"id":"5429f2c0498e94f30de6b53d","name":"Things to try","description":"","type":"others","user":{"id":"80433546","firstName":"Samantha","lastName":"Gansz","gender":"female","photo":{"prefix":"https:\/\/fastly.4sqi.net\/img\/user\/","suffix":"\/80433546-UBWL0KUER52P2UK0.jpg"}},"editable":false,"public":true,"collaborative":false,"url":"\/user\/80433546\/list\/things-to-try","canonicalUrl":"https:\/\/foursquare.com\/user\/80433546\/list\/things-to-try","createdAt":1412035264,"updatedAt":1412035380,"photo":{"id":"51bbaabf498ee95f2086a7a2","createdAt":1371253439,"prefix":"https:\/\/fastly.4sqi.net\/img\/general\/","suffix":"\/377802_WQawA3qCV0pgSEIrVGpysLWnr64Q3UBw1Q4CfWBGfpk.jpg","width":612,"height":612,"user":{"id":"377802","firstName":"Ben","lastName":"Ostrowsky","gender":"none","photo":{"prefix":"https:\/\/fastly.4sqi.net\/img\/user\/","suffix":"\/377802_ea0b4Myy_fqko5AG4Ih2f54StbBEPtWV9ylWgzJosUoxY3WjtMRyjoVa6iKv3bd4BPr3gLdyW.jpg"}},"visibility":"public"},"followers":{"count":0},"listItems":{"count":4,"items":[{"id":"v4d629262b6b9a1cd16e29351","createdAt":1412035380}]}}]}]},"pageUpdates":{"count":0,"items":[]},"inbox":{"count":0,"items":[]},"attributes":{"groups":[{"type":"price","name":"Price","summary":"$$","count":1,"items":[{"displayName":"Price","displayValue":"$$","priceTier":2}]},{"type":"reservations","name":"Reservations","summary":"Reservations","count":3,"items":[{"displayName":"Reservations","displayValue":"Yes"}]}]},"bestPhoto":{"id":"5bd35826a35dce002c3aa527","createdAt":1540577318,"source":{"name":"Swarm for iOS","url":"https:\/\/www.swarmapp.com"},"prefix":"https:\/\/fastly.4sqi.net\/img\/general\/","suffix":"\/70098888_ed1BuoivufnCOTt4QqDPZZcCUyLR1_nyta_abfzJT4w.jpg","width":1440,"height":1920,"visibility":"public"},"colors":{"highlightColor":{"photoId":"5bd35826a35dce002c3aa527","value":-15198192},"highlightTextColor":{"photoId":"5bd35826a35dce002c3aa527","value":-1},"algoVersion":3}}}}