{"meta":{"code":200,"requestId":"5d29395b8ad62e002cdc9963"},"response":{"venue":{"id":"4e7b9e9cb9936323aac3d778","name":"Westfield Brandon Mall Food Court","contact":{},"location":{"address":"459 Brandon Town Center Mall","lat":27.932359697480933,"lng":-82.32531325021066,"labeledLatLngs":[{"label":"display","lat":27.932359697480933,"lng":-82.32531325021066}],"cc":"US","state":"Florida","country":"United States","formattedAddress":["459 Brandon Town Center Mall","Florida","United States"]},"canonicalUrl":"https:\/\/foursquare.com\/v\/westfield-brandon-mall-food-court\/4e7b9e9cb9936323aac3d778","categories":[{"id":"4bf58dd8d48988d120951735","name":"Food Court","pluralName":"Food Courts","shortName":"Food Court","icon":{"prefix":"https:\/\/ss3.4sqi.net\/img\/categories_v2\/shops\/food_foodcourt_","suffix":".png"},"primary":true}],"verified":false,"stats":{"tipCount":5},"likes":{"count":66,"groups":[{"type":"others","count":66,"items":[]}],"summary":"66 Likes"},"dislike":false,"ok":false,"rating":8.1,"ratingColor":"73CF42","ratingSignals":79,"allowMenuUrlEdit":true,"beenHere":{"count":0,"unconfirmedCount":0,"marked":false,"lastCheckinExpiredAt":0},"specials":{"count":0,"items":[]},"photos":{"count":23,"groups":[{"type":"checkin","name":"Friends' check-in photos","count":0,"items":[]},{"type":"venue","name":"Venue photos","count":23,"items":[{"id":"5138e479e4b07fcab3e8a5c2","createdAt":1362683001,"source":{"name":"Foursquare for iOS","url":"https:\/\/foursquare.com\/download\/#\/iphone"},"prefix":"https:\/\/fastly.4sqi.net\/img\/general\/","suffix":"\/2552011_ItP81yIWQ8Eomt6c28VwEh4jU-NmV5gpPq47hC74QnY.jpg","width":720,"height":960,"user":{"id":"2552011","firstName":"Gabe","lastName":"Barreto","gender":"male","photo":{"prefix":"https:\/\/fastly.4sqi.net\/img\/user\/","suffix":"\/2552011-MMRHMASK1RTH5EXE.jpg"}},"visibility":"public"},{"id":"5047ab65e4b0a21d2f99ed41","createdAt":1346874213,"source":{"name":"Foursquare for iOS","url":"https:\/\/foursquare.com\/download\/#\/iphone"},"prefix":"https:\/\/fastly.4sqi.net\/img\/general\/","suffix":"\/Gw0aNqpoM-cMdyQc0uOi5CiYYVswpQ7gA7UOsQMb_3M.jpg","width":720,"height":540,"user":{"id":"704562","firstName":"Cyndee","lastName":"Haydon","gender":"female","photo":{"prefix":"https:\/\/fastly.4sqi.net\/img\/user\/","suffix":"\/HRX3HPEIFZYALNFD.jpg"}},"visibility":"public"}]}],"summary":"0 photos"},"reasons":{"count":1,"items":[{"summary":"Lots of people like this place","type":"general","reasonName":"rawLikesReason"}]},"hereNow":{"count":0,"summary":"Nobody here","groups":[]},"createdAt":1316724380,"tips":{"count":5,"groups":[{"type":"others","name":"All tips","count":5,"items":[{"id":"52c1a744498edf026c8f73ef","createdAt":1388422980,"text":"Very slow crowds","type":"user","canonicalUrl":"https:\/\/foursquare.com\/item\/52c1a744498edf026c8f73ef","lang":"en","likes":{"count":5,"groups":[{"type":"others","count":5,"items":[{"id":"3304538","firstName":"Trapper","gender":"male","photo":{"prefix":"https:\/\/fastly.4sqi.net\/img\/user\/","suffix":"\/3304538-0IC1RPUVBBP00E3Q.jpg"}},{"id":"67354570","firstName":"Frédéric","lastName":"P","gender":"male","photo":{"prefix":"https:\/\/fastly.4sqi.net\/img\/user\/","suffix":"\/67354570-5FT1TOA1PSTGGZYS.jpg"}},{"id":"25060545","firstName":"fermin","lastName":"alvarez","gender":"male","photo":{"prefix":"https:\/\/fastly.4sqi.net\/img\/user\/","suffix":"\/25060545-X2RJCSFEM4WM4DQY.jpg"}},{"id":"57706491","firstName":"Khristian","lastName":"Torres","gender":"male","photo":{"prefix":"https:\/\/fastly.4sqi.net\/img\/user\/","suffix":"\/57706491-KB0RY0RX0J4JCWVF.jpg"}}]}],"summary":"5 likes"},"logView":true,"agreeCount":6,"disagreeCount":0,"todo":{"count":0},"user":{"id":"47384187","firstName":"Mike","lastName":"Bentley","gender":"male","photo":{"prefix":"https:\/\/fastly.4sqi.net\/img\/user\/","suffix":"\/47384187-KG2O3WQZQLX0ZH2L.jpg"}},"authorInteractionType":"liked"},{"id":"4e7b9f36d1646ee5c1ef83c2","createdAt":1316724534,"text":"Free refills if you work in the mall!","type":"user","canonicalUrl":"https:\/\/foursquare.com\/item\/4e7b9f36d1646ee5c1ef83c2","lang":"en","likes":{"count":2,"groups":[{"type":"others","count":2,"items":[{"id":"3304538","firstName":"Trapper","gender":"male","photo":{"prefix":"https:\/\/fastly.4sqi.net\/img\/user\/","suffix":"\/3304538-0IC1RPUVBBP00E3Q.jpg"}},{"id":"17560662","firstName":"Eric","lastName":"Newell","gender":"male","photo":{"prefix":"https:\/\/fastly.4sqi.net\/img\/user\/","suffix":"\/MNJ1MSH2MT5OSVY2.jpg"}}]}],"summary":"2 likes"},"logView":true,"agreeCount":2,"disagreeCount":0,"todo":{"count":0},"user":{"id":"10690085","firstName":"Heidy Lee","gender":"female","photo":{"prefix":"https:\/\/fastly.4sqi.net\/img\/user\/","suffix":"\/402Q5Q35KGZWE4AN.jpg"}}}]}]},"shortUrl":"http:\/\/4sq.com\/oH5Llk","timeZone":"America\/New_York","listed":{"count":3,"groups":[{"type":"others","name":"Lists from other people","count":3,"items":[{"id":"4ef64e4eb63446a507df3891","name":"shopping","description":"","type":"others","user":{"id":"17857270","firstName":"Gloria","lastName":"Plymale","gender":"female","photo":{"prefix":"https:\/\/fastly.4sqi.net\/img\/user\/","suffix":"\/17857270-S2ZPO40FMTT3HT4V.jpg"}},"editable":false,"public":true,"collaborative":false,"url":"\/user\/17857270\/list\/shopping","canonicalUrl":"https:\/\/foursquare.com\/user\/17857270\/list\/shopping","createdAt":1324764750,"updatedAt":1523566575,"followers":{"count":8},"listItems":{"count":55,"items":[{"id":"v4e7b9e9cb9936323aac3d778","createdAt":1332162923}]}},{"id":"506b122ce4b0b35efbc15545","name":"FOOD!","description":"","type":"others","user":{"id":"28128638","firstName":"BC","lastName":";)","gender":"female","photo":{"prefix":"https:\/\/fastly.4sqi.net\/img\/user\/","suffix":"\/J4ARWCZZZVUVZZJK.jpg"}},"editable":false,"public":true,"collaborative":false,"url":"\/red9nose\/list\/food","canonicalUrl":"https:\/\/foursquare.com\/red9nose\/list\/food","createdAt":1349194284,"updatedAt":1370183152,"followers":{"count":1},"listItems":{"count":82,"items":[{"id":"v4e7b9e9cb9936323aac3d778","createdAt":1351799066}]}}]}]},"popular":{"isOpen":false,"isLocalHoliday":false,"timeframes":[{"days":"Today","includesToday":true,"open":[{"renderedTime":"11:00 AM\u20139:00 PM"}],"segments":[]},{"days":"Sat","open":[{"renderedTime":"11:00 AM\u20139:00 PM"}],"segments":[]},{"days":"Sun","open":[{"renderedTime":"11:00 AM\u20136:00 PM"}],"segments":[]},{"days":"Mon","open":[{"renderedTime":"Noon\u20137:00 PM"}],"segments":[]},{"days":"Tue\u2013Wed","open":[{"renderedTime":"11:00 AM\u20138:00 PM"}],"segments":[]},{"days":"Thu","open":[{"renderedTime":"Noon\u20138:00 PM"}],"segments":[]}]},"pageUpdates":{"count":0,"items":[]},"inbox":{"count":0,"items":[]},"parent":{"id":"4b2bad68f964a52006b924e3","name":"Westfield Brandon","location":{"address":"459 Brandon Town Center Mall","lat":27.93232440426672,"lng":-82.32613680069295,"postalCode":"33511","cc":"US","city":"Brandon","state":"FL","country":"United States","formattedAddress":["459 Brandon Town Center Mall","Brandon, FL 33511","United States"]},"categories":[{"id":"4bf58dd8d48988d1fd941735","name":"Shopping Mall","pluralName":"Shopping Malls","shortName":"Mall","icon":{"prefix":"https:\/\/ss3.4sqi.net\/img\/categories_v2\/shops\/mall_","suffix":".png"},"primary":true}]},"hierarchy":[{"name":"Westfield Brandon","lang":"en","id":"4b2bad68f964a52006b924e3","canonicalUrl":"https:\/\/foursquare.com\/v\/westfield-brandon\/4b2bad68f964a52006b924e3"}],"attributes":{"groups":[{"type":"payments","name":"Credit Cards","summary":"Credit Cards","count":7,"items":[{"displayName":"Credit Cards","displayValue":"Yes (incl. American Express)"}]},{"type":"music","name":"Music","summary":"Music","count":3,"items":[{"displayName":"Music","displayValue":"Yes"}]},{"type":"wifi","name":"Wi-Fi","summary":"Wi-Fi","count":1,"items":[{"displayName":"Wi-Fi","displayValue":"Yes"}]},{"type":"serves","name":"Menus","summary":"Dinner, Lunch & more","count":8,"items":[{"displayName":"Brunch","displayValue":"Brunch"},{"displayName":"Lunch","displayValue":"Lunch"},{"displayName":"Dinner","displayValue":"Dinner"}]},{"type":"drinks","name":"Drinks","summary":"Cocktails","count":5,"items":[{"displayName":"Cocktails","displayValue":"Cocktails"}]}]},"bestPhoto":{"id":"5138e479e4b07fcab3e8a5c2","createdAt":1362683001,"source":{"name":"Foursquare for iOS","url":"https:\/\/foursquare.com\/download\/#\/iphone"},"prefix":"https:\/\/fastly.4sqi.net\/img\/general\/","suffix":"\/2552011_ItP81yIWQ8Eomt6c28VwEh4jU-NmV5gpPq47hC74QnY.jpg","width":720,"height":960,"visibility":"public"},"colors":{"highlightColor":{"photoId":"5138e479e4b07fcab3e8a5c2","value":-13621232},"highlightTextColor":{"photoId":"5138e479e4b07fcab3e8a5c2","value":-1},"algoVersion":3}}}}